nerva_numpy/__init__.py
nerva_numpy/activation_functions.py
nerva_numpy/datasets.py
nerva_numpy/layers.py
nerva_numpy/learning_rate.py
nerva_numpy/loss_functions.py
nerva_numpy/matrix_operations.py
nerva_numpy/multilayer_perceptron.py
nerva_numpy/optimizers.py
nerva_numpy/softmax_functions.py
nerva_numpy/training.py
nerva_numpy/utilities.py
nerva_numpy/weight_initializers.py
nerva_numpy-0.9.0.dist-info/licenses/LICENSE
nerva_numpy-0.9.0.dist-info/METADATA
nerva_numpy-0.9.0.dist-info/WHEEL
nerva_numpy-0.9.0.dist-info/top_level.txt
nerva_numpy-0.9.0.dist-info/RECORD
